lectes/__init__.py
lectes/errors.py
lectes/config/__init__.py
lectes/config/models.py
lectes/engine/__init__.py
lectes/engine/errors.py
lectes/engine/models.py
lectes/scanner/__init__.py
lectes/scanner/logger.py
lectes/scanner/models.py
lectes/scanner/scanner.py
lectes/tests/__init__.py
lectes/tests/unit/__init__.py
lectes/tests/unit/engine/__init__.py
lectes/tests/unit/engine/test_models.py
lectes/tests/unit/scanner/__init__.py
lectes/tests/unit/scanner/test_scanner.py
lectes-0.2.0.dist-info/licenses/LICENSE
lectes-0.2.0.dist-info/METADATA
lectes-0.2.0.dist-info/WHEEL
lectes-0.2.0.dist-info/top_level.txt
lectes-0.2.0.dist-info/RECORD
