Metadata-Version: 2.4
Name: lectes
Version: 0.2.0
Summary: Add your description here
Requires-Python: >=3.13
License-File: LICENSE
Dynamic: license-file
